fastapi_endpoints/__init__.py
fastapi_endpoints/constants.py
fastapi_endpoints/exceptions.py
fastapi_endpoints/router.py
fastapi_endpoints/utils.py
fastapi_endpoints-0.1.2.dist-info/METADATA
fastapi_endpoints-0.1.2.dist-info/WHEEL
fastapi_endpoints-0.1.2.dist-info/licenses/LICENSE
fastapi_endpoints-0.1.2.dist-info/RECORD
