Metadata-Version: 2.4
Name: fastapi-endpoints
Version: 0.1.2
Summary: A file based router for FastAPI that helps with defining endpoints
License: MIT
License-File: LICENSE
Author: Vlad Nedelcu
Author-email: nedelcuvd@gmail.com
Requires-Python: >=3.8,<4.0
Classifier: License :: OSI Approved :: MIT License
Classifier: Programming Language :: Python :: 3
Classifier: Programming Language :: Python :: 3.8
Classifier: Programming Language :: Python :: 3.9
Classifier: Programming Language :: Python :: 3.10
Classifier: Programming Language :: Python :: 3.11
Classifier: Programming Language :: Python :: 3.12
Classifier: Programming Language :: Python :: 3.13
Classifier: Programming Language :: Python :: 3.14
Requires-Dist: fastapi (>=0.112.4)
